mongo_wrapper/__init__.py
mongo_wrapper/error_handlers.py
mongo_wrapper/mongo_wrapper.py
mongo_wrapper/test/__init__.py
mongo_wrapper/test/test_error_handlers.py
mongo_wrapper/test/test_mongo_wrapper.py
mongo_wrapper-1.0.0.dist-info/METADATA
mongo_wrapper-1.0.0.dist-info/RECORD
mongo_wrapper-1.0.0.dist-info/WHEEL
mongo_wrapper-1.0.0.dist-info/top_level.txt
